pyapi_service_kit/__init__.py
pyapi_service_kit/db/__init__.py
pyapi_service_kit/db/generic.py
pyapi_service_kit/db/testing.py
pyapi_service_kit/logging.yaml
pyapi_service_kit/nats/__init__.py
pyapi_service_kit/nats/config.py
pyapi_service_kit/nats/core.py
pyapi_service_kit/nats/jetstream.py
pyapi_service_kit/nats/kv.py
pyapi_service_kit/nats/nats_payload.py
pyapi_service_kit/nats/tasks.py
pyapi_service_kit/py.typed
pyapi_service_kit/service/__init__.py
pyapi_service_kit/service/config.py
pyapi_service_kit/service/guid.py
pyapi_service_kit/service/readiness.py
pyapi_service_kit/time/__init__.py
pyapi_service_kit/time/parser.py
pyapi_service_kit/time/temporal_scheduler.py
pyapi_service_kit/utils/__init__.py
pyapi_service_kit/utils/initalisation.py
pyapi_service_kit/utils/nested_enum.py
pyapi_service_kit/utils/templated_enum.py
pyapi_service_kit-0.0.16.dist-info/LICENSE
pyapi_service_kit-0.0.16.dist-info/METADATA
pyapi_service_kit-0.0.16.dist-info/WHEEL
pyapi_service_kit-0.0.16.dist-info/RECORD
